switchboard/__init__.py
switchboard/cords.py
switchboard/diggable.py
switchboard/exceptions.py
switchboard/switchboard.py
tests/__init__.py
tests/test_switchboard.py
python_switchboard-0.0.1.dist-info/LICENSE
python_switchboard-0.0.1.dist-info/METADATA
python_switchboard-0.0.1.dist-info/WHEEL
python_switchboard-0.0.1.dist-info/top_level.txt
python_switchboard-0.0.1.dist-info/RECORD
