Metadata-Version: 2.1
Name: python-switchboard
Version: 0.0.1
Summary: A lightweight package for converting JSON schemas
Home-page: https://github.com/juhoen/Switchboard
Author: Juho Enala
Author-email: juho.enala@gmail.com
License: UNKNOWN
Platform: UNKNOWN
Classifier: Programming Language :: Python :: 3
Classifier: License :: OSI Approved :: MIT License
Classifier: Operating System :: OS Independent
Requires-Python: >=3.6
